wavmark/__init__.py
wavmark/models/__init__.py
wavmark/models/hinet.py
wavmark/models/invblock.py
wavmark/models/module_util.py
wavmark/models/my_model.py
wavmark/models/rrdb_denselayer.py
wavmark/utils/__init__.py
wavmark/utils/file_reader.py
wavmark/utils/metric_util.py
wavmark/utils/my_parser.py
wavmark/utils/path_util.py
wavmark/utils/wm_add_util.py
wavmark/utils/wm_decode_util.py
wavmark-0.0.2.dist-info/METADATA
wavmark-0.0.2.dist-info/WHEEL
wavmark-0.0.2.dist-info/licenses/LICENSE
wavmark-0.0.2.dist-info/RECORD
