Metadata-Version: 2.1
Name: wavmark
Version: 0.0.2
Summary: AI-Based Audio Watermarking Tool
Project-URL: Homepage, https://github.com/wavmark/wavmark
Project-URL: Bug Tracker, https://github.com/wavmark/wavmark/issues
Author-email: "Guangyu Chen (RUC)" <v-chenguangyu@outlook.com>
License-File: LICENSE
Classifier: License :: OSI Approved :: MIT License
Classifier: Operating System :: OS Independent
Classifier: Programming Language :: Python :: 3
Requires-Python: >=3.6
Requires-Dist: huggingface-hub
Requires-Dist: librosa
Requires-Dist: resampy
Requires-Dist: torch<2.0
Requires-Dist: torchaudio<2.0
Requires-Dist: tqdm
